[
  {
    "full_name": "Unleash/unleash",
    "stargazers_count": 8518,
    "open_issues_count": 51,
    "forks_count": 533
  },
  {
    "full_name": "AnuragRoy485/Weather-Forecast-Analysis",
    "stargazers_count": 1,
    "open_issues_count": 0,
    "forks_count": 0
  },
  {
    "full_name": "Sayanss99/Weather-Forecast-Analysis",
    "stargazers_count": 2,
    "open_issues_count": 0,
    "forks_count": 1
  },
  {
    "full_name": "AnuragRoy485/Awesome-CyberSec-Resources",
    "stargazers_count": 1,
    "open_issues_count": 0,
    "forks_count": 0
  },
  {
    "full_name": "AnuragRoy485/competitive-programming",
    "stargazers_count": 1,
    "open_issues_count": 0,
    "forks_count": 0
  },
  {
    "full_name": "AnuragRoy485/register",
    "stargazers_count": 1,
    "open_issues_count": 0,
    "forks_count": 0
  },
  {
    "full_name": "AnuragRoy485/code-server",
    "stargazers_count": 1,
    "open_issues_count": 0,
    "forks_count": 0
  },
  {
    "full_name": "dikshantrajput/Hacktoberfest-accepted-2022",
    "stargazers_count": 124,
    "open_issues_count": 453,
    "forks_count": 499
  },
  {
    "full_name": "Py-Contributors/awesomeScripts",
    "stargazers_count": 488,
    "open_issues_count": 7,
    "forks_count": 262
  },
  {
    "full_name": "AnuragRoy485/Hacktoberfest-2022",
    "stargazers_count": 1,
    "open_issues_count": 0,
    "forks_count": 0
  },
  {
    "full_name": "keshavsingh4522/hacktoberfest2021",
    "stargazers_count": 793,
    "open_issues_count": 2905,
    "forks_count": 3856
  },
  {
    "full_name": "AnuragRoy485/L3MON",
    "stargazers_count": 1,
    "open_issues_count": 0,
    "forks_count": 0
  },
  {
    "full_name": "AnuragRoy485/GitHubGraduation-2022",
    "stargazers_count": 1,
    "open_issues_count": 0,
    "forks_count": 0
  },
  {
    "full_name": "atsign-foundation/at_client_sdk",
    "stargazers_count": 1513,
    "open_issues_count": 100,
    "forks_count": 31
  },
  {
    "full_name": "AnuragRoy485/HLavalink",
    "stargazers_count": 1,
    "open_issues_count": 0,
    "forks_count": 0
  }
]